coinaddrvalidator/__init__.py
coinaddrvalidator/attrs_zope.py
coinaddrvalidator/base.py
coinaddrvalidator/currency.py
coinaddrvalidator/interfaces.py
coinaddrvalidator/validation.py
coinaddrvalidator/encoding/__init__.py
coinaddrvalidator/encoding/crc16.py
tests/__init__.py
tests/test_coinaddr.py
tests/test_currency.py
tests/test_validation.py
coinaddrvalidator-1.2.3.dist-info/LICENSE
coinaddrvalidator-1.2.3.dist-info/METADATA
coinaddrvalidator-1.2.3.dist-info/WHEEL
coinaddrvalidator-1.2.3.dist-info/top_level.txt
coinaddrvalidator-1.2.3.dist-info/RECORD
