Metadata-Version: 2.1
Name: coinaddrvalidator
Version: 1.2.3
Summary: A crypto-currency address inspection/validation library.
Home-page: https://github.com/nobitex/coinaddrvalid
Download-URL: https://github.com/nobitex/coinaddrvalid/tarball/v1.2.3
Author: Mohammad Aghamir
Author-email: maghamir@nobitex.net
Maintainer: Mohammad Aghamir
Maintainer-email: maghamir@nobitex.net
License: MIT
Keywords: bitcoin,litecoin,altcoin,ethereum,address,validation,inspection
Classifier: Development Status :: 4 - Beta
Classifier: Intended Audience :: Developers
Classifier: Operating System :: OS Independent
Classifier: Natural Language :: English
Classifier: License :: OSI Approved :: MIT License
Classifier: Programming Language :: Python :: 3
Classifier: Programming Language :: Python :: 3.4
Classifier: Programming Language :: Python :: 3.5
Classifier: Programming Language :: Python :: 3.6
Classifier: Programming Language :: Python :: 3.7
Classifier: Programming Language :: Python :: 3.8
Classifier: Programming Language :: Python :: 3.9
Classifier: Programming Language :: Python :: 3.10
Classifier: Programming Language :: Python :: 3.11
Classifier: Programming Language :: Python :: 3.12
Classifier: Programming Language :: Python :: 3 :: Only
Classifier: Topic :: Internet :: WWW/HTTP
Classifier: Topic :: Software Development
Classifier: Topic :: Security :: Cryptography
Classifier: Topic :: Text Processing
Classifier: Topic :: Utilities
Classifier: Topic :: Software Development :: Libraries :: Python Modules
License-File: LICENSE
Requires-Dist: attrs >=24.0.0
Requires-Dist: pycryptodome >=3.6.1
Requires-Dist: base58check >=1.0.1
Requires-Dist: zope.interface >=4.4.3
Requires-Dist: blake256 >=0.1.1
Requires-Dist: cbor >=1.0.0
Requires-Dist: bech32 >=1.1.0
Requires-Dist: groestlcoin-hash2 >=1.1.1
Requires-Dist: zope
